{"data": [{"date": "2025-12-16T09:00:00", "open": 327.25, "high": 327.25, "low": 327.25, "close": 327.25, "volume": 108}, {"date": "2025-12-16T12:00:00", "open": 326.5, "high": 326.5, "low": 326.5, "close": 326.5, "volume": 803}, {"date": "2025-12-16T13:00:00", "open": 325.0, "high": 325.0, "low": 325.0, "close": 325.0, "volume": 324}, {"date": "2025-12-16T17:00:00", "open": 325.0, "high": 325.0, "low": 325.0, "close": 325.0, "volume": 747}, {"date": "2025-12-16T18:00:00", "open": 325.75, "high": 325.75, "low": 325.75, "close": 325.75, "volume": 521}, {"date": "2025-12-17T09:00:00", "open": 325.0, "high": 325.0, "low": 325.0, "close": 325.0, "volume": 226}, {"date": "2025-12-17T12:00:00", "open": 322.25, "high": 322.25, "low": 322.25, "close": 322.25, "volume": 1341}, {"date": "2025-12-17T13:00:00", "open": 321.25, "high": 321.25, "low": 321.25, "close": 321.25, "volume": 1434}, {"date": "2025-12-17T17:00:00", "open": 320.0, "high": 320.0, "low": 320.0, "close": 320.0, "volume": 2997}, {"date": "2025-12-17T18:00:00", "open": 316.5, "high": 316.5, "low": 316.5, "close": 316.5, "volume": 736}, {"date": "2025-12-18T09:00:00", "open": 316.0, "high": 316.0, "low": 316.0, "close": 316.0, "volume": 1181}, {"date": "2025-12-18T12:00:00", "open": 316.0, "high": 316.0, "low": 316.0, "close": 316.0, "volume": 2916}, {"date": "2025-12-18T13:00:00", "open": 316.5, "high": 316.5, "low": 316.5, "close": 316.5, "volume": 560}, {"date": "2025-12-18T17:00:00", "open": 316.75, "high": 316.75, "low": 316.75, "close": 316.75, "volume": 1469}, {"date": "2025-12-18T18:00:00", "open": 320.0, "high": 320.0, "low": 320.0, "close": 320.0, "volume": 400}, {"date": "2025-12-19T09:00:00", "open": 320.25, "high": 320.25, "low": 320.25, "close": 320.25, "volume": 162}, {"date": "2025-12-19T12:00:00", "open": 320.0, "high": 320.0, "low": 320.0, "close": 320.0, "volume": 490}, {"date": "2025-12-19T13:00:00", "open": 318.5, "high": 318.5, "low": 318.5, "close": 318.5, "volume": 141}, {"date": "2025-12-19T17:00:00", "open": 308.5, "high": 308.5, "low": 308.5, "close": 308.5, "volume": 3016}, {"date": "2025-12-19T18:00:00", "open": 315.75, "high": 315.75, "low": 315.75, "close": 315.75, "volume": 468}, {"date": "2025-12-22T09:00:00", "open": 316.25, "high": 316.25, "low": 316.25, "close": 316.25, "volume": 390}, {"date": "2025-12-22T12:00:00", "open": 316.25, "high": 316.25, "low": 316.25, "close": 316.25, "volume": 3180}, {"date": "2025-12-22T13:00:00", "open": 318.0, "high": 318.0, "low": 318.0, "close": 318.0, "volume": 1038}, {"date": "2025-12-22T17:00:00", "open": 316.0, "high": 316.0, "low": 316.0, "close": 316.0, "volume": 987}, {"date": "2025-12-22T18:00:00", "open": 318.0, "high": 318.0, "low": 318.0, "close": 318.0, "volume": 486}, {"date": "2025-12-23T09:00:00", "open": 325.0, "high": 325.0, "low": 325.0, "close": 325.0, "volume": 594}, {"date": "2025-12-23T12:00:00", "open": 325.0, "high": 325.0, "low": 325.0, "close": 325.0, "volume": 1532}, {"date": "2025-12-23T13:00:00", "open": 320.5, "high": 320.5, "low": 320.5, "close": 320.5, "volume": 502}, {"date": "2025-12-23T17:00:00", "open": 319.0, "high": 319.0, "low": 319.0, "close": 319.0, "volume": 2893}, {"date": "2025-12-23T18:00:00", "open": 319.0, "high": 319.0, "low": 319.0, "close": 319.0, "volume": 346}, {"date": "2025-12-24T09:00:00", "open": 319.0, "high": 319.0, "low": 319.0, "close": 319.0, "volume": 129}, {"date": "2025-12-24T12:00:00", "open": 318.75, "high": 318.75, "low": 318.75, "close": 318.75, "volume": 986}, {"date": "2025-12-24T13:00:00", "open": 316.0, "high": 316.0, "low": 316.0, "close": 316.0, "volume": 600}, {"date": "2025-12-24T17:00:00", "open": 318.75, "high": 318.75, "low": 318.75, "close": 318.75, "volume": 3139}, {"date": "2025-12-24T18:00:00", "open": 318.75, "high": 318.75, "low": 318.75, "close": 318.75, "volume": 601}, {"date": "2025-12-25T09:00:00", "open": 320.0, "high": 320.0, "low": 320.0, "close": 320.0, "volume": 49}, {"date": "2025-12-25T12:00:00", "open": 320.0, "high": 320.0, "low": 320.0, "close": 320.0, "volume": 1448}, {"date": "2025-12-25T13:00:00", "open": 320.0, "high": 320.0, "low": 320.0, "close": 320.0, "volume": 1908}, {"date": "2025-12-25T17:00:00", "open": 320.0, "high": 320.0, "low": 320.0, "close": 320.0, "volume": 1083}, {"date": "2025-12-25T18:00:00", "open": 325.0, "high": 325.0, "low": 325.0, "close": 325.0, "volume": 216}, {"date": "2025-12-26T09:00:00", "open": 325.0, "high": 325.0, "low": 325.0, "close": 325.0, "volume": 200}, {"date": "2025-12-26T12:00:00", "open": 324.75, "high": 324.75, "low": 324.75, "close": 324.75, "volume": 730}, {"date": "2025-12-26T13:00:00", "open": 324.0, "high": 324.0, "low": 324.0, "close": 324.0, "volume": 711}, {"date": "2025-12-26T17:00:00", "open": 322.5, "high": 322.5, "low": 322.5, "close": 322.5, "volume": 2138}, {"date": "2025-12-26T18:00:00", "open": 322.5, "high": 322.5, "low": 322.5, "close": 322.5, "volume": 110}, {"date": "2025-12-29T09:00:00", "open": 308.0, "high": 308.0, "low": 308.0, "close": 308.0, "volume": 1570}, {"date": "2025-12-29T12:00:00", "open": 330.0, "high": 330.0, "low": 330.0, "close": 330.0, "volume": 1557}, {"date": "2025-12-29T13:00:00", "open": 335.0, "high": 335.0, "low": 335.0, "close": 335.0, "volume": 3255}, {"date": "2025-12-29T17:00:00", "open": 335.0, "high": 335.0, "low": 335.0, "close": 335.0, "volume": 2049}, {"date": "2025-12-29T18:00:00", "open": 332.0, "high": 332.0, "low": 332.0, "close": 332.0, "volume": 168}, {"date": "2025-12-30T09:00:00", "open": 332.0, "high": 332.0, "low": 332.0, "close": 332.0, "volume": 1540}, {"date": "2025-12-30T12:00:00", "open": 332.0, "high": 332.0, "low": 332.0, "close": 332.0, "volume": 4889}, {"date": "2025-12-30T13:00:00", "open": 325.0, "high": 325.0, "low": 325.0, "close": 325.0, "volume": 283}, {"date": "2025-12-30T17:00:00", "open": 325.0, "high": 325.0, "low": 325.0, "close": 325.0, "volume": 986}, {"date": "2025-12-30T18:00:00", "open": 325.25, "high": 325.25, "low": 325.25, "close": 325.25, "volume": 370}, {"date": "2025-12-31T09:00:00", "open": 326.25, "high": 326.25, "low": 326.25, "close": 326.25, "volume": 151}, {"date": "2025-12-31T12:00:00", "open": 345.5, "high": 345.5, "low": 345.5, "close": 345.5, "volume": 3428}, {"date": "2025-12-31T13:00:00", "open": 345.5, "high": 345.5, "low": 345.5, "close": 345.5, "volume": 4081}, {"date": "2025-12-31T17:00:00", "open": 345.5, "high": 345.5, "low": 345.5, "close": 345.5, "volume": 1951}, {"date": "2025-12-31T18:00:00", "open": 344.0, "high": 344.0, "low": 344.0, "close": 344.0, "volume": 221}, {"date": "2026-01-02T09:00:00", "open": 350.5, "high": 350.5, "low": 350.5, "close": 350.5, "volume": 891}, {"date": "2026-01-02T12:00:00", "open": 350.5, "high": 350.5, "low": 350.5, "close": 350.5, "volume": 3713}, {"date": "2026-01-02T13:00:00", "open": 349.5, "high": 349.5, "low": 349.5, "close": 349.5, "volume": 547}, {"date": "2026-01-02T17:00:00", "open": 349.5, "high": 349.5, "low": 349.5, "close": 349.5, "volume": 1176}, {"date": "2026-01-02T18:00:00", "open": 349.0, "high": 349.0, "low": 349.0, "close": 349.0, "volume": 182}, {"date": "2026-01-05T09:00:00", "open": 346.25, "high": 346.25, "low": 346.25, "close": 346.25, "volume": 690}, {"date": "2026-01-05T12:00:00", "open": 345.0, "high": 345.0, "low": 345.0, "close": 345.0, "volume": 797}, {"date": "2026-01-05T13:00:00", "open": 344.5, "high": 344.5, "low": 344.5, "close": 344.5, "volume": 714}, {"date": "2026-01-05T17:00:00", "open": 341.0, "high": 341.0, "low": 341.0, "close": 341.0, "volume": 1454}, {"date": "2026-01-05T18:00:00", "open": 339.5, "high": 339.5, "low": 339.5, "close": 339.5, "volume": 253}, {"date": "2026-01-06T09:00:00", "open": 339.5, "high": 339.5, "low": 339.5, "close": 339.5, "volume": 1002}, {"date": "2026-01-06T12:00:00", "open": 335.5, "high": 335.5, "low": 335.5, "close": 335.5, "volume": 1362}, {"date": "2026-01-06T13:00:00", "open": 335.0, "high": 335.0, "low": 335.0, "close": 335.0, "volume": 587}, {"date": "2026-01-06T17:00:00", "open": 335.0, "high": 335.0, "low": 335.0, "close": 335.0, "volume": 4519}, {"date": "2026-01-06T18:00:00", "open": 334.5, "high": 334.5, "low": 334.5, "close": 334.5, "volume": 356}, {"date": "2026-01-07T09:00:00", "open": 334.0, "high": 334.0, "low": 334.0, "close": 334.0, "volume": 964}, {"date": "2026-01-07T12:00:00", "open": 333.25, "high": 333.25, "low": 333.25, "close": 333.25, "volume": 3141}, {"date": "2026-01-07T13:00:00", "open": 333.0, "high": 333.0, "low": 333.0, "close": 333.0, "volume": 1680}, {"date": "2026-01-07T17:00:00", "open": 330.0, "high": 330.0, "low": 330.0, "close": 330.0, "volume": 1943}, {"date": "2026-01-07T18:00:00", "open": 329.0, "high": 329.0, "low": 329.0, "close": 329.0, "volume": 628}, {"date": "2026-01-08T09:00:00", "open": 328.75, "high": 328.75, "low": 328.75, "close": 328.75, "volume": 413}, {"date": "2026-01-08T12:00:00", "open": 326.0, "high": 326.0, "low": 326.0, "close": 326.0, "volume": 1551}, {"date": "2026-01-08T13:00:00", "open": 325.5, "high": 325.5, "low": 325.5, "close": 325.5, "volume": 790}, {"date": "2026-01-08T17:00:00", "open": 325.5, "high": 325.5, "low": 325.5, "close": 325.5, "volume": 1294}, {"date": "2026-01-08T18:00:00", "open": 326.5, "high": 326.5, "low": 326.5, "close": 326.5, "volume": 591}, {"date": "2026-01-09T09:00:00", "open": 326.5, "high": 326.5, "low": 326.5, "close": 326.5, "volume": 508}, {"date": "2026-01-09T12:00:00", "open": 328.0, "high": 328.0, "low": 328.0, "close": 328.0, "volume": 1769}, {"date": "2026-01-09T13:00:00", "open": 335.0, "high": 335.0, "low": 335.0, "close": 335.0, "volume": 707}, {"date": "2026-01-09T17:00:00", "open": 347.0, "high": 347.0, "low": 347.0, "close": 347.0, "volume": 2088}, {"date": "2026-01-09T18:00:00", "open": 340.0, "high": 340.0, "low": 340.0, "close": 340.0, "volume": 245}, {"date": "2026-01-12T09:00:00", "open": 355.0, "high": 355.0, "low": 355.0, "close": 355.0, "volume": 2152}, {"date": "2026-01-12T12:00:00", "open": 355.0, "high": 355.0, "low": 355.0, "close": 355.0, "volume": 4327}, {"date": "2026-01-12T13:00:00", "open": 350.0, "high": 350.0, "low": 350.0, "close": 350.0, "volume": 610}, {"date": "2026-01-12T17:00:00", "open": 349.5, "high": 349.5, "low": 349.5, "close": 349.5, "volume": 2802}, {"date": "2026-01-12T18:00:00", "open": 348.75, "high": 348.75, "low": 348.75, "close": 348.75, "volume": 173}, {"date": "2026-01-13T09:00:00", "open": 348.75, "high": 348.75, "low": 348.75, "close": 348.75, "volume": 216}, {"date": "2026-01-13T12:00:00", "open": 350.0, "high": 350.0, "low": 350.0, "close": 350.0, "volume": 2174}, {"date": "2026-01-13T13:00:00", "open": 350.0, "high": 350.0, "low": 350.0, "close": 350.0, "volume": 1090}, {"date": "2026-01-13T17:00:00", "open": 349.5, "high": 349.5, "low": 349.5, "close": 349.5, "volume": 934}, {"date": "2026-01-13T18:00:00", "open": 349.0, "high": 349.0, "low": 349.0, "close": 349.0, "volume": 403}, {"date": "2026-01-14T09:00:00", "open": 344.25, "high": 344.25, "low": 344.25, "close": 344.25, "volume": 243}, {"date": "2026-01-14T12:00:00", "open": 344.25, "high": 344.25, "low": 344.25, "close": 344.25, "volume": 2329}, {"date": "2026-01-14T13:00:00", "open": 344.0, "high": 344.0, "low": 344.0, "close": 344.0, "volume": 1173}, {"date": "2026-01-14T17:00:00", "open": 343.0, "high": 343.0, "low": 343.0, "close": 343.0, "volume": 1601}, {"date": "2026-01-14T18:00:00", "open": 343.0, "high": 343.0, "low": 343.0, "close": 343.0, "volume": 557}, {"date": "2026-01-15T09:00:00", "open": 330.0, "high": 330.0, "low": 330.0, "close": 330.0, "volume": 579}, {"date": "2026-01-15T12:00:00", "open": 335.0, "high": 335.0, "low": 335.0, "close": 335.0, "volume": 3866}, {"date": "2026-01-15T13:00:00", "open": 334.75, "high": 334.75, "low": 334.75, "close": 334.75, "volume": 1241}, {"date": "2026-01-15T17:00:00", "open": 335.0, "high": 335.0, "low": 335.0, "close": 335.0, "volume": 2209}, {"date": "2026-01-15T18:00:00", "open": 335.0, "high": 335.0, "low": 335.0, "close": 335.0, "volume": 976}, {"date": "2026-01-16T09:00:00", "open": 326.75, "high": 326.75, "low": 326.75, "close": 326.75, "volume": 404}, {"date": "2026-01-16T12:00:00", "open": 330.0, "high": 330.0, "low": 330.0, "close": 330.0, "volume": 2243}, {"date": "2026-01-16T13:00:00", "open": 330.0, "high": 330.0, "low": 330.0, "close": 330.0, "volume": 610}, {"date": "2026-01-16T17:00:00", "open": 333.0, "high": 333.0, "low": 333.0, "close": 333.0, "volume": 659}, {"date": "2026-01-16T18:00:00", "open": 333.0, "high": 333.0, "low": 333.0, "close": 333.0, "volume": 1314}, {"date": "2026-01-19T09:00:00", "open": 340.0, "high": 340.0, "low": 340.0, "close": 340.0, "volume": 381}, {"date": "2026-01-19T12:00:00", "open": 340.0, "high": 340.0, "low": 340.0, "close": 340.0, "volume": 2310}, {"date": "2026-01-19T13:00:00", "open": 340.0, "high": 340.0, "low": 340.0, "close": 340.0, "volume": 987}, {"date": "2026-01-19T17:00:00", "open": 340.0, "high": 340.0, "low": 340.0, "close": 340.0, "volume": 890}, {"date": "2026-01-19T18:00:00", "open": 337.25, "high": 337.25, "low": 337.25, "close": 337.25, "volume": 97}, {"date": "2026-01-20T09:00:00", "open": 332.0, "high": 332.0, "low": 332.0, "close": 332.0, "volume": 205}, {"date": "2026-01-20T12:00:00", "open": 327.5, "high": 327.5, "low": 327.5, "close": 327.5, "volume": 3101}, {"date": "2026-01-20T13:00:00", "open": 332.0, "high": 332.0, "low": 332.0, "close": 332.0, "volume": 285}, {"date": "2026-01-20T17:00:00", "open": 332.0, "high": 332.0, "low": 332.0, "close": 332.0, "volume": 4870}, {"date": "2026-01-20T18:00:00", "open": 331.0, "high": 331.0, "low": 331.0, "close": 331.0, "volume": 222}, {"date": "2026-01-21T09:00:00", "open": 331.0, "high": 331.0, "low": 331.0, "close": 331.0, "volume": 241}, {"date": "2026-01-21T12:00:00", "open": 331.0, "high": 331.0, "low": 331.0, "close": 331.0, "volume": 1463}, {"date": "2026-01-21T13:00:00", "open": 330.0, "high": 330.0, "low": 330.0, "close": 330.0, "volume": 300}, {"date": "2026-01-21T17:00:00", "open": 326.0, "high": 326.0, "low": 326.0, "close": 326.0, "volume": 919}, {"date": "2026-01-21T18:00:00", "open": 324.25, "high": 324.25, "low": 324.25, "close": 324.25, "volume": 490}, {"date": "2026-01-22T09:00:00", "open": 325.0, "high": 325.0, "low": 325.0, "close": 325.0, "volume": 462}, {"date": "2026-01-22T12:00:00", "open": 325.0, "high": 325.0, "low": 325.0, "close": 325.0, "volume": 1132}, {"date": "2026-01-22T13:00:00", "open": 325.0, "high": 325.0, "low": 325.0, "close": 325.0, "volume": 1455}, {"date": "2026-01-22T17:00:00", "open": 325.0, "high": 325.0, "low": 325.0, "close": 325.0, "volume": 1467}, {"date": "2026-01-22T18:00:00", "open": 327.5, "high": 327.5, "low": 327.5, "close": 327.5, "volume": 105}, {"date": "2026-01-23T09:00:00", "open": 327.5, "high": 327.5, "low": 327.5, "close": 327.5, "volume": 260}, {"date": "2026-01-23T12:00:00", "open": 327.5, "high": 327.5, "low": 327.5, "close": 327.5, "volume": 1593}, {"date": "2026-01-23T13:00:00", "open": 327.5, "high": 327.5, "low": 327.5, "close": 327.5, "volume": 2270}, {"date": "2026-01-23T17:00:00", "open": 327.25, "high": 327.25, "low": 327.25, "close": 327.25, "volume": 2163}, {"date": "2026-01-23T18:00:00", "open": 327.25, "high": 327.25, "low": 327.25, "close": 327.25, "volume": 803}, {"date": "2026-01-26T09:00:00", "open": 327.0, "high": 327.0, "low": 327.0, "close": 327.0, "volume": 512}, {"date": "2026-01-26T12:00:00", "open": 327.0, "high": 327.0, "low": 327.0, "close": 327.0, "volume": 2180}, {"date": "2026-01-26T13:00:00", "open": 327.0, "high": 327.0, "low": 327.0, "close": 327.0, "volume": 2414}, {"date": "2026-01-26T17:00:00", "open": 326.5, "high": 326.5, "low": 326.5, "close": 326.5, "volume": 904}, {"date": "2026-01-26T18:00:00", "open": 326.0, "high": 326.0, "low": 326.0, "close": 326.0, "volume": 760}, {"date": "2026-01-27T09:00:00", "open": 326.0, "high": 326.0, "low": 326.0, "close": 326.0, "volume": 276}, {"date": "2026-01-27T12:00:00", "open": 322.0, "high": 322.0, "low": 322.0, "close": 322.0, "volume": 1727}, {"date": "2026-01-27T13:00:00", "open": 321.5, "high": 321.5, "low": 321.5, "close": 321.5, "volume": 1958}, {"date": "2026-01-27T17:00:00", "open": 321.5, "high": 321.5, "low": 321.5, "close": 321.5, "volume": 1520}, {"date": "2026-01-27T18:00:00", "open": 321.5, "high": 321.5, "low": 321.5, "close": 321.5, "volume": 1055}, {"date": "2026-01-28T09:00:00", "open": 321.5, "high": 321.5, "low": 321.5, "close": 321.5, "volume": 806}, {"date": "2026-01-28T12:00:00", "open": 321.5, "high": 321.5, "low": 321.5, "close": 321.5, "volume": 7713}, {"date": "2026-01-28T13:00:00", "open": 322.25, "high": 322.25, "low": 322.25, "close": 322.25, "volume": 990}, {"date": "2026-01-28T17:00:00", "open": 322.5, "high": 322.5, "low": 322.5, "close": 322.5, "volume": 755}, {"date": "2026-01-28T18:00:00", "open": 322.5, "high": 322.5, "low": 322.5, "close": 322.5, "volume": 1111}, {"date": "2026-01-29T09:00:00", "open": 325.5, "high": 325.5, "low": 325.5, "close": 325.5, "volume": 62}, {"date": "2026-01-29T12:00:00", "open": 325.5, "high": 325.5, "low": 325.5, "close": 325.5, "volume": 2680}, {"date": "2026-01-29T13:00:00", "open": 325.5, "high": 325.5, "low": 325.5, "close": 325.5, "volume": 2252}, {"date": "2026-01-29T17:00:00", "open": 325.5, "high": 325.5, "low": 325.5, "close": 325.5, "volume": 3577}, {"date": "2026-01-29T18:00:00", "open": 325.25, "high": 325.25, "low": 325.25, "close": 325.25, "volume": 468}, {"date": "2026-01-30T09:00:00", "open": 325.5, "high": 325.5, "low": 325.5, "close": 325.5, "volume": 445}, {"date": "2026-01-30T12:00:00", "open": 325.5, "high": 325.5, "low": 325.5, "close": 325.5, "volume": 2033}, {"date": "2026-01-30T13:00:00", "open": 330.0, "high": 330.0, "low": 330.0, "close": 330.0, "volume": 314}, {"date": "2026-01-30T17:00:00", "open": 330.0, "high": 330.0, "low": 330.0, "close": 330.0, "volume": 2107}, {"date": "2026-01-30T18:00:00", "open": 331.75, "high": 331.75, "low": 331.75, "close": 331.75, "volume": 184}, {"date": "2026-02-02T09:00:00", "open": 334.0, "high": 334.0, "low": 334.0, "close": 334.0, "volume": 719}, {"date": "2026-02-02T12:00:00", "open": 335.0, "high": 335.0, "low": 335.0, "close": 335.0, "volume": 1721}, {"date": "2026-02-02T13:00:00", "open": 336.0, "high": 336.0, "low": 336.0, "close": 336.0, "volume": 2056}, {"date": "2026-02-02T17:00:00", "open": 336.25, "high": 336.25, "low": 336.25, "close": 336.25, "volume": 3384}, {"date": "2026-02-02T18:00:00", "open": 336.0, "high": 336.0, "low": 336.0, "close": 336.0, "volume": 258}, {"date": "2026-02-03T09:00:00", "open": 346.0, "high": 346.0, "low": 346.0, "close": 346.0, "volume": 1495}, {"date": "2026-02-03T12:00:00", "open": 350.0, "high": 350.0, "low": 350.0, "close": 350.0, "volume": 3012}, {"date": "2026-02-03T13:00:00", "open": 351.0, "high": 351.0, "low": 351.0, "close": 351.0, "volume": 1694}, {"date": "2026-02-03T17:00:00", "open": 353.0, "high": 353.0, "low": 353.0, "close": 353.0, "volume": 2329}, {"date": "2026-02-03T18:00:00", "open": 353.25, "high": 353.25, "low": 353.25, "close": 353.25, "volume": 2481}, {"date": "2026-02-04T09:00:00", "open": 355.0, "high": 355.0, "low": 355.0, "close": 355.0, "volume": 683}, {"date": "2026-02-04T12:00:00", "open": 355.0, "high": 355.0, "low": 355.0, "close": 355.0, "volume": 2455}, {"date": "2026-02-04T13:00:00", "open": 328.5, "high": 328.5, "low": 328.5, "close": 328.5, "volume": 2050}, {"date": "2026-02-04T17:00:00", "open": 364.75, "high": 364.75, "low": 364.75, "close": 364.75, "volume": 2324}, {"date": "2026-02-04T18:00:00", "open": 364.0, "high": 364.0, "low": 364.0, "close": 364.0, "volume": 3855}, {"date": "2026-02-05T09:00:00", "open": 356.5, "high": 356.5, "low": 356.5, "close": 356.5, "volume": 1256}, {"date": "2026-02-05T12:00:00", "open": 355.5, "high": 355.5, "low": 355.5, "close": 355.5, "volume": 3130}, {"date": "2026-02-05T13:00:00", "open": 355.5, "high": 355.5, "low": 355.5, "close": 355.5, "volume": 4574}, {"date": "2026-02-05T17:00:00", "open": 355.25, "high": 355.25, "low": 355.25, "close": 355.25, "volume": 3617}, {"date": "2026-02-05T18:00:00", "open": 344.75, "high": 344.75, "low": 344.75, "close": 344.75, "volume": 797}, {"date": "2026-02-06T09:00:00", "open": 344.25, "high": 344.25, "low": 344.25, "close": 344.25, "volume": 1356}, {"date": "2026-02-06T12:00:00", "open": 344.25, "high": 344.25, "low": 344.25, "close": 344.25, "volume": 1688}, {"date": "2026-02-06T13:00:00", "open": 344.25, "high": 344.25, "low": 344.25, "close": 344.25, "volume": 443}, {"date": "2026-02-06T17:00:00", "open": 344.0, "high": 344.0, "low": 344.0, "close": 344.0, "volume": 1336}, {"date": "2026-02-06T18:00:00", "open": 344.0, "high": 344.0, "low": 344.0, "close": 344.0, "volume": 629}, {"date": "2026-02-09T09:00:00", "open": 344.0, "high": 344.0, "low": 344.0, "close": 344.0, "volume": 1422}, {"date": "2026-02-09T12:00:00", "open": 344.0, "high": 344.0, "low": 344.0, "close": 344.0, "volume": 2100}, {"date": "2026-02-09T13:00:00", "open": 344.0, "high": 344.0, "low": 344.0, "close": 344.0, "volume": 967}, {"date": "2026-02-09T17:00:00", "open": 349.5, "high": 349.5, "low": 349.5, "close": 349.5, "volume": 1665}, {"date": "2026-02-09T18:00:00", "open": 359.75, "high": 359.75, "low": 359.75, "close": 359.75, "volume": 929}, {"date": "2026-02-10T09:00:00", "open": 360.0, "high": 360.0, "low": 360.0, "close": 360.0, "volume": 1711}, {"date": "2026-02-10T12:00:00", "open": 363.0, "high": 363.0, "low": 363.0, "close": 363.0, "volume": 2034}, {"date": "2026-02-10T13:00:00", "open": 363.0, "high": 363.0, "low": 363.0, "close": 363.0, "volume": 1318}, {"date": "2026-02-10T17:00:00", "open": 364.0, "high": 364.0, "low": 364.0, "close": 364.0, "volume": 1781}, {"date": "2026-02-10T18:00:00", "open": 364.0, "high": 364.0, "low": 364.0, "close": 364.0, "volume": 292}, {"date": "2026-02-11T09:00:00", "open": 360.0, "high": 360.0, "low": 360.0, "close": 360.0, "volume": 608}, {"date": "2026-02-11T12:00:00", "open": 359.75, "high": 359.75, "low": 359.75, "close": 359.75, "volume": 1118}, {"date": "2026-02-11T13:00:00", "open": 357.75, "high": 357.75, "low": 357.75, "close": 357.75, "volume": 454}, {"date": "2026-02-11T17:00:00", "open": 356.0, "high": 356.0, "low": 356.0, "close": 356.0, "volume": 1853}, {"date": "2026-02-11T18:00:00", "open": 350.0, "high": 350.0, "low": 350.0, "close": 350.0, "volume": 903}, {"date": "2026-02-12T09:00:00", "open": 350.0, "high": 350.0, "low": 350.0, "close": 350.0, "volume": 506}, {"date": "2026-02-12T12:00:00", "open": 350.75, "high": 350.75, "low": 350.75, "close": 350.75, "volume": 2491}, {"date": "2026-02-12T13:00:00", "open": 352.25, "high": 352.25, "low": 352.25, "close": 352.25, "volume": 225}, {"date": "2026-02-12T17:00:00", "open": 353.0, "high": 353.0, "low": 353.0, "close": 353.0, "volume": 2077}, {"date": "2026-02-12T18:00:00", "open": 353.0, "high": 353.0, "low": 353.0, "close": 353.0, "volume": 747}, {"date": "2026-02-13T09:00:00", "open": 351.75, "high": 351.75, "low": 351.75, "close": 351.75, "volume": 184}, {"date": "2026-02-13T12:00:00", "open": 353.0, "high": 353.0, "low": 353.0, "close": 353.0, "volume": 3115}, {"date": "2026-02-13T13:00:00", "open": 362.5, "high": 362.5, "low": 362.5, "close": 362.5, "volume": 1105}, {"date": "2026-02-13T17:00:00", "open": 370.25, "high": 370.25, "low": 370.25, "close": 370.25, "volume": 2543}, {"date": "2026-02-13T18:00:00", "open": 371.25, "high": 371.25, "low": 371.25, "close": 371.25, "volume": 1925}, {"date": "2026-02-16T09:00:00", "open": 371.25, "high": 371.25, "low": 371.25, "close": 371.25, "volume": 4363}, {"date": "2026-02-16T12:00:00", "open": 382.25, "high": 382.25, "low": 382.25, "close": 382.25, "volume": 1180}, {"date": "2026-02-16T13:00:00", "open": 387.75, "high": 387.75, "low": 387.75, "close": 387.75, "volume": 2219}, {"date": "2026-02-16T17:00:00", "open": 387.5, "high": 387.5, "low": 387.5, "close": 387.5, "volume": 4177}, {"date": "2026-02-16T18:00:00", "open": 386.75, "high": 386.75, "low": 386.75, "close": 386.75, "volume": 85}, {"date": "2026-02-17T09:00:00", "open": 389.25, "high": 389.25, "low": 389.25, "close": 389.25, "volume": 1152}, {"date": "2026-02-17T12:00:00", "open": 389.25, "high": 389.25, "low": 389.25, "close": 389.25, "volume": 2127}, {"date": "2026-02-17T13:00:00", "open": 372.0, "high": 372.0, "low": 372.0, "close": 372.0, "volume": 1155}, {"date": "2026-02-17T17:00:00", "open": 353.75, "high": 353.75, "low": 353.75, "close": 353.75, "volume": 5416}, {"date": "2026-02-17T18:00:00", "open": 354.0, "high": 354.0, "low": 354.0, "close": 354.0, "volume": 3094}, {"date": "2026-02-18T09:00:00", "open": 352.0, "high": 352.0, "low": 352.0, "close": 352.0, "volume": 2054}, {"date": "2026-02-18T12:00:00", "open": 352.25, "high": 352.25, "low": 352.25, "close": 352.25, "volume": 4086}, {"date": "2026-02-18T13:00:00", "open": 352.25, "high": 352.25, "low": 352.25, "close": 352.25, "volume": 1156}, {"date": "2026-02-18T17:00:00", "open": 350.0, "high": 350.0, "low": 350.0, "close": 350.0, "volume": 2393}, {"date": "2026-02-18T18:00:00", "open": 345.0, "high": 345.0, "low": 345.0, "close": 345.0, "volume": 1745}, {"date": "2026-02-19T09:00:00", "open": 340.0, "high": 340.0, "low": 340.0, "close": 340.0, "volume": 1006}, {"date": "2026-02-19T12:00:00", "open": 350.25, "high": 350.25, "low": 350.25, "close": 350.25, "volume": 3625}, {"date": "2026-02-19T13:00:00", "open": 354.5, "high": 354.5, "low": 354.5, "close": 354.5, "volume": 844}, {"date": "2026-02-19T17:00:00", "open": 350.25, "high": 350.25, "low": 350.25, "close": 350.25, "volume": 2219}, {"date": "2026-02-19T18:00:00", "open": 350.25, "high": 350.25, "low": 350.25, "close": 350.25, "volume": 4286}, {"date": "2026-02-20T09:00:00", "open": 345.0, "high": 345.0, "low": 345.0, "close": 345.0, "volume": 625}, {"date": "2026-02-20T12:00:00", "open": 355.0, "high": 355.0, "low": 355.0, "close": 355.0, "volume": 955}, {"date": "2026-02-20T13:00:00", "open": 350.0, "high": 350.0, "low": 350.0, "close": 350.0, "volume": 368}, {"date": "2026-02-20T17:00:00", "open": 355.0, "high": 355.0, "low": 355.0, "close": 355.0, "volume": 1235}, {"date": "2026-02-20T18:00:00", "open": 355.0, "high": 355.0, "low": 355.0, "close": 355.0, "volume": 1088}, {"date": "2026-02-23T09:00:00", "open": 359.25, "high": 359.25, "low": 359.25, "close": 359.25, "volume": 754}, {"date": "2026-02-23T12:00:00", "open": 359.25, "high": 359.25, "low": 359.25, "close": 359.25, "volume": 2047}, {"date": "2026-02-23T13:00:00", "open": 359.0, "high": 359.0, "low": 359.0, "close": 359.0, "volume": 1052}, {"date": "2026-02-23T17:00:00", "open": 358.0, "high": 358.0, "low": 358.0, "close": 358.0, "volume": 753}, {"date": "2026-02-23T18:00:00", "open": 355.5, "high": 355.5, "low": 355.5, "close": 355.5, "volume": 201}, {"date": "2026-02-24T09:00:00", "open": 352.0, "high": 352.0, "low": 352.0, "close": 352.0, "volume": 269}, {"date": "2026-02-24T12:00:00", "open": 349.0, "high": 349.0, "low": 349.0, "close": 349.0, "volume": 847}, {"date": "2026-02-24T13:00:00", "open": 350.75, "high": 350.75, "low": 350.75, "close": 350.75, "volume": 544}, {"date": "2026-02-24T17:00:00", "open": 350.75, "high": 350.75, "low": 350.75, "close": 350.75, "volume": 690}, {"date": "2026-02-24T18:00:00", "open": 350.75, "high": 350.75, "low": 350.75, "close": 350.75, "volume": 547}, {"date": "2026-02-25T09:00:00", "open": 350.75, "high": 350.75, "low": 350.75, "close": 350.75, "volume": 2111}, {"date": "2026-02-25T12:00:00", "open": 350.0, "high": 350.0, "low": 350.0, "close": 350.0, "volume": 2049}, {"date": "2026-02-25T13:00:00", "open": 345.25, "high": 345.25, "low": 345.25, "close": 345.25, "volume": 401}, {"date": "2026-02-25T17:00:00", "open": 345.25, "high": 345.25, "low": 345.25, "close": 345.25, "volume": 1633}, {"date": "2026-02-25T18:00:00", "open": 343.5, "high": 343.5, "low": 343.5, "close": 343.5, "volume": 1248}]}